{
	"configurations" : 
	[
		{
			"directories" : 
			[
				{
					"build" : ".",
					"childIndexes" : 
					[
						1,
						2
					],
					"minimumCMakeVersion" : 
					{
						"string" : "3.0"
					},
					"projectIndex" : 0,
					"source" : "."
				},
				{
					"build" : "src",
					"minimumCMakeVersion" : 
					{
						"string" : "3.0"
					},
					"parentIndex" : 0,
					"projectIndex" : 0,
					"source" : "src",
					"targetIndexes" : 
					[
						1
					]
				},
				{
					"build" : "example",
					"childIndexes" : 
					[
						3,
						4
					],
					"minimumCMakeVersion" : 
					{
						"string" : "3.0"
					},
					"parentIndex" : 0,
					"projectIndex" : 0,
					"source" : "example"
				},
				{
					"build" : "example/Callee",
					"minimumCMakeVersion" : 
					{
						"string" : "3.0"
					},
					"parentIndex" : 2,
					"projectIndex" : 0,
					"source" : "example/Callee",
					"targetIndexes" : 
					[
						2
					]
				},
				{
					"build" : "example/Caller",
					"minimumCMakeVersion" : 
					{
						"string" : "3.0"
					},
					"parentIndex" : 2,
					"projectIndex" : 0,
					"source" : "example/Caller",
					"targetIndexes" : 
					[
						0
					]
				}
			],
			"name" : "Debug",
			"projects" : 
			[
				{
					"directoryIndexes" : 
					[
						0,
						1,
						2,
						3,
						4
					],
					"name" : "mprpc",
					"targetIndexes" : 
					[
						0,
						1,
						2
					]
				}
			],
			"targets" : 
			[
				{
					"directoryIndex" : 4,
					"id" : "consumer::@c47e23a0647e12c7d706",
					"jsonFile" : "target-consumer-Debug-9b44f86c0ac020d9a1ac.json",
					"name" : "consumer",
					"projectIndex" : 0
				},
				{
					"directoryIndex" : 1,
					"id" : "mprpc::@145eef247bfb46b6828c",
					"jsonFile" : "target-mprpc-Debug-b806894c758775f36ca4.json",
					"name" : "mprpc",
					"projectIndex" : 0
				},
				{
					"directoryIndex" : 3,
					"id" : "provider::@45178d15422ea211a888",
					"jsonFile" : "target-provider-Debug-994f89a24798f19ea41e.json",
					"name" : "provider",
					"projectIndex" : 0
				}
			]
		}
	],
	"kind" : "codemodel",
	"paths" : 
	{
		"build" : "/home/yangzhan/mprpc/mprpc/build",
		"source" : "/home/yangzhan/mprpc/mprpc"
	},
	"version" : 
	{
		"major" : 2,
		"minor" : 0
	}
}
